lofty/__init__.py
lofty/module1.py
loftyfamily-0.2.dist-info/licenses/LICENSE
loftyfamily-0.2.dist-info/METADATA
loftyfamily-0.2.dist-info/WHEEL
loftyfamily-0.2.dist-info/top_level.txt
loftyfamily-0.2.dist-info/RECORD
