Metadata-Version: 2.4
Name: loftyfamily
Version: 0.2
Summary: A python library focused on providing up to date insights and information on Hazel Lofty
Home-page: https://github.com/Violevo/loftyfamily
Author: Oliver Fisher
Classifier: Programming Language :: Python :: 3
Classifier: License :: OSI Approved :: MIT License
Classifier: Operating System :: OS Independent
Requires-Python: >=3.6
License-File: LICENSE
Dynamic: author
Dynamic: classifier
Dynamic: description
Dynamic: description-content-type
Dynamic: home-page
Dynamic: license-file
Dynamic: requires-python
Dynamic: summary
